dc_client/__init__.py
dc_client/dc_client.py
dc_client-0.0.113.dist-info/LICENSE
dc_client-0.0.113.dist-info/METADATA
dc_client-0.0.113.dist-info/WHEEL
dc_client-0.0.113.dist-info/top_level.txt
dc_client-0.0.113.dist-info/RECORD
