Metadata-Version: 2.1
Name: dc-client
Version: 0.0.113
Summary: Data Catalog Client
Home-page: https://github.com/stonezhong/DataManager/tree/master/client/dc_client
Author: Stone Zhong
Author-email: stonezhong@hotmail.com
License: MIT
Platform: UNKNOWN
Classifier: License :: OSI Approved :: MIT License
Classifier: Programming Language :: Python :: 3
Requires-Dist: requests
